awsv2_auth.py
requests_awsv2_auth-1.1.3.dist-info/LICENSE
requests_awsv2_auth-1.1.3.dist-info/METADATA
requests_awsv2_auth-1.1.3.dist-info/WHEEL
requests_awsv2_auth-1.1.3.dist-info/top_level.txt
requests_awsv2_auth-1.1.3.dist-info/RECORD
