Metadata-Version: 2.1
Name: requests-awsv2-auth
Version: 1.1.3
Summary: AWS v2 auth support for Python-Requests.
Home-page: https://github.com/brutasse/requests-awsv2-auth
Author: Bruno Renié
Author-email: UNKNOWN
License: BSD
Platform: any
Classifier: Intended Audience :: Developers
Classifier: Intended Audience :: System Administrators
Classifier: License :: OSI Approved :: BSD License
Classifier: Operating System :: OS Independent
Classifier: Programming Language :: Python
Classifier: Programming Language :: Python :: 2
Classifier: Programming Language :: Python :: 3
Requires-Dist: requests
